datatransformpackage/__init__.py
datatransformpackage/dataTransformLib.py
datatransformpackage-1.0.dist-info/METADATA
datatransformpackage-1.0.dist-info/WHEEL
datatransformpackage-1.0.dist-info/RECORD
