Metadata-Version: 2.1
Name: datatransformpackage
Version: 1.0
Summary: POC of a Python library that will help Data Scientist do transform their data
Author: Petra
Requires-Python: >=3.12,<4.0
Classifier: Programming Language :: Python :: 3
Classifier: Programming Language :: Python :: 3.12
Requires-Dist: numpy (==1.26.4)
